rfmt/__init__.py
rfmt/base.py
rfmt/blocks.py
rfmt/support.py
sql_parser/__init__.py
sql_parser/cmd.py
sql_parser/const.py
sql_parser/dml.py
sql_parser/expr.py
sql_parser/expr_base.py
sql_parser/expr_funcs.py
sql_parser/expr_op.py
sql_parser/func.py
sql_parser/ident.py
sql_parser/lexer.py
sql_parser/node.py
sql_parser/parser.py
sql_parser/query.py
sql_parser/query_impl.py
sql_parser/test_const.py
sql_parser/test_expr.py
sql_parser/test_expr_op.py
sql_parser/test_parser.py
sql_parser/test_sql_lexer.py
sql_parser/types.py
sql_parser/utils.py
sql_refactor/__init__.py
sql_refactor-0.0.6.dist-info/LICENSE
sql_refactor-0.0.6.dist-info/METADATA
sql_refactor-0.0.6.dist-info/WHEEL
sql_refactor-0.0.6.dist-info/top_level.txt
sql_refactor-0.0.6.dist-info/RECORD
