Metadata-Version: 2.1
Name: sql-refactor
Version: 0.0.6
Summary: Transform column and table name to desired one
Home-page: https://github.com/maztohir/sample-sql-translator
Author: Muhamad Tohir
Author-email: maztohir@gmail.com
License: UNKNOWN
Project-URL: Bug Tracker, https://github.com/maztohir/sample-sql-translator/issues
Platform: UNKNOWN
Classifier: Programming Language :: Python :: 3
Classifier: License :: OSI Approved :: MIT License
Classifier: Operating System :: OS Independent
Requires-Python: >=3.7.9
